bewcore_yespower.cp38-win_amd64.pyd
bewcore_yespower-1.0.2.dist-info/LICENSE
bewcore_yespower-1.0.2.dist-info/METADATA
bewcore_yespower-1.0.2.dist-info/WHEEL
bewcore_yespower-1.0.2.dist-info/top_level.txt
bewcore_yespower-1.0.2.dist-info/RECORD
